[
  {
    "name": "推荐",
    "list": [
      {
        "name": "嵘基系列",
        "icon": "https://gitee.com/UserRJZC/rjgitee/raw/Admin/icon/%E7%9A%AE%E5%8D%A1%E4%B8%98.jpg"
      },
      {
        "name": "免费开源",
        "icon": "https://gitee.com/UserRJZC/rjgitee/raw/Admin/icon/%E7%9A%AE%E5%8D%A1%E4%B8%98.jpg"
      },
      {
        "name": "学习使用",
        "icon": "https://gitee.com/UserRJZC/rjgitee/raw/Admin/icon/%E7%9A%AE%E5%8D%A1%E4%B8%98.jpg"
      },
      {
        "name": "禁止商用",
        "icon": "https://gitee.com/UserRJZC/rjgitee/raw/Admin/icon/%E7%9A%AE%E5%8D%A1%E4%B8%98.jpg"
      },
      {
        "name": "禁止买卖",
        "icon": "https://gitee.com/UserRJZC/rjgitee/raw/Admin/icon/%E7%9A%AE%E5%8D%A1%E4%B8%98.jpg"
      }
    ]
  },
  {
    "name": "嵘基系列软件『全部免费』",
    "list": [
      {
        "name": "嵘基影音大屏版",
        "url": "https://d.kstore.dev/download/15123/APK/%E5%B5%98%E5%9F%BA%E5%BD%B1%E9%9F%B32.6.2%E5%A4%A7%E5%B1%8F%E9%80%9A%E7%94%A8%E7%89%88.apk",
        "icon": "https://gitee.com/UserRJZC/rjgitee/raw/Admin/icon/%E7%9A%AE%E5%8D%A1%E4%B8%98.jpg",
        "version": "V2.6.2[armeabi-v7a]"
      },
      {
        "name": "嵘基影音大屏版",
        "url": "https://d.kstore.dev/download/15123/APK/%E5%B5%98%E5%9F%BA%E5%BD%B1%E9%9F%B32.6.2%E5%A4%A7%E5%B1%8F64%E4%BD%8D%E7%89%88.apk",
        "icon": "https://gitee.com/UserRJZC/rjgitee/raw/Admin/icon/%E7%9A%AE%E5%8D%A1%E4%B8%98.jpg",
        "version": "V2.6.2[arm64-v8a]"
      },
      {
        "name": "嵘基影音竖屏版",
        "url": "https://d.kstore.dev/download/15123/APK/%E5%B5%98%E5%9F%BA%E5%BD%B1%E9%9F%B32.6.2%E7%AB%96%E5%B1%8F64%E4%BD%8D%E7%89%88.apk",
        "icon": "https://gitee.com/UserRJZC/rjgitee/raw/Admin/icon/%E7%9A%AE%E5%8D%A1%E4%B8%98.jpg",
        "version": "V2.6.2[arm64-v8a]"
      }
    ]
  }
]
